jscrawler/__init__.py
jscrawler/jscrawler.py
jscrawler-0.0.3.dist-info/METADATA
jscrawler-0.0.3.dist-info/WHEEL
jscrawler-0.0.3.dist-info/entry_points.txt
jscrawler-0.0.3.dist-info/top_level.txt
jscrawler-0.0.3.dist-info/RECORD
