Metadata-Version: 2.1
Name: jscrawler
Version: 0.0.3
Requires-Dist: beautifulsoup4==4.11.1
Requires-Dist: requests==2.25.1
